frameshift/__init__.py
frameshift/analyzer.py
frameshift/chunker.py
frameshift/config.py
frameshift/connection.py
frameshift/core.py
frameshift/exceptions.py
frameshift/py.typed
frameshift/schema.py
frameshift/types.py
frameshift-0.1.0.dist-info/METADATA
frameshift-0.1.0.dist-info/WHEEL
frameshift-0.1.0.dist-info/licenses/LICENSE
frameshift-0.1.0.dist-info/RECORD
