Metadata-Version: 2.4
Name: frameshift
Version: 0.1.0
Summary: Load pandas DataFrames into Amazon Redshift without S3 - using the somewhat-efficient multi-row INSERT statement AWS Redshift offers
Project-URL: Homepage, https://github.com/lcapece/frameshift
Project-URL: Documentation, https://frameshift.readthedocs.io
Project-URL: Repository, https://github.com/lcapece/frameshift
Project-URL: Issues, https://github.com/lcapece/frameshift/issues
Project-URL: Changelog, https://github.com/lcapece/frameshift/blob/main/CHANGELOG.md
Author-email: "Louis N. Capece" <lcapece@optonline.net>
Maintainer-email: "Louis N. Capece" <lcapece@optonline.net>
License: MIT
License-File: LICENSE
Keywords: bulk-insert,data loading,dataframe,insert,multi-row-insert,no-s3,pandas,redshift,without s3
Classifier: Development Status :: 4 - Beta
Classifier: Intended Audience :: Developers
Classifier: Intended Audience :: Science/Research
Classifier: License :: OSI Approved :: MIT License
Classifier: Operating System :: OS Independent
Classifier: Programming Language :: Python :: 3
Classifier: Programming Language :: Python :: 3.9
Classifier: Programming Language :: Python :: 3.10
Classifier: Programming Language :: Python :: 3.11
Classifier: Programming Language :: Python :: 3.12
Classifier: Programming Language :: Python :: 3.13
Classifier: Topic :: Database
Classifier: Topic :: Scientific/Engineering
Classifier: Topic :: Software Development :: Libraries :: Python Modules
Classifier: Typing :: Typed
Requires-Python: >=3.9
Requires-Dist: numpy>=1.21.0
Requires-Dist: pandas>=1.5.0
Requires-Dist: psycopg2-binary>=2.9.0
Provides-Extra: all
Requires-Dist: black>=23.0.0; extra == 'all'
Requires-Dist: mypy>=1.0.0; extra == 'all'
Requires-Dist: myst-parser>=2.0.0; extra == 'all'
Requires-Dist: pandas-stubs>=2.0.0; extra == 'all'
Requires-Dist: pytest-cov>=4.0.0; extra == 'all'
Requires-Dist: pytest-mock>=3.10.0; extra == 'all'
Requires-Dist: pytest>=7.0.0; extra == 'all'
Requires-Dist: redshift-connector>=2.0.0; extra == 'all'
Requires-Dist: ruff>=0.1.0; extra == 'all'
Requires-Dist: sphinx-rtd-theme>=2.0.0; extra == 'all'
Requires-Dist: sphinx>=7.0.0; extra == 'all'
Requires-Dist: sqlalchemy-redshift>=0.8.0; extra == 'all'
Requires-Dist: sqlalchemy>=2.0.0; extra == 'all'
Provides-Extra: dev
Requires-Dist: black>=23.0.0; extra == 'dev'
Requires-Dist: mypy>=1.0.0; extra == 'dev'
Requires-Dist: pandas-stubs>=2.0.0; extra == 'dev'
Requires-Dist: pytest-cov>=4.0.0; extra == 'dev'
Requires-Dist: pytest-mock>=3.10.0; extra == 'dev'
Requires-Dist: pytest>=7.0.0; extra == 'dev'
Requires-Dist: ruff>=0.1.0; extra == 'dev'
Provides-Extra: docs
Requires-Dist: myst-parser>=2.0.0; extra == 'docs'
Requires-Dist: sphinx-rtd-theme>=2.0.0; extra == 'docs'
Requires-Dist: sphinx>=7.0.0; extra == 'docs'
Provides-Extra: redshift-connector
Requires-Dist: redshift-connector>=2.0.0; extra == 'redshift-connector'
Provides-Extra: sqlalchemy
Requires-Dist: sqlalchemy-redshift>=0.8.0; extra == 'sqlalchemy'
Requires-Dist: sqlalchemy>=2.0.0; extra == 'sqlalchemy'
